py.typed
clerk_dev/__init__.py
clerk_dev/_hooks/__init__.py
clerk_dev/_hooks/registration.py
clerk_dev/_hooks/sdkhooks.py
clerk_dev/_hooks/types.py
clerk_dev/actortokens.py
clerk_dev/allowlistidentifiers.py
clerk_dev/basesdk.py
clerk_dev/betafeatures.py
clerk_dev/blocklistidentifiers_sdk.py
clerk_dev/clients.py
clerk_dev/domains_sdk.py
clerk_dev/emailaddresses.py
clerk_dev/httpclient.py
clerk_dev/instancesettings_sdk.py
clerk_dev/invitations.py
clerk_dev/jwks.py
clerk_dev/jwttemplates.py
clerk_dev/misc.py
clerk_dev/models/__init__.py
clerk_dev/models/actortoken.py
clerk_dev/models/adddomainop.py
clerk_dev/models/allowlistidentifier.py
clerk_dev/models/banuserop.py
clerk_dev/models/blocklistidentifier.py
clerk_dev/models/blocklistidentifiers.py
clerk_dev/models/changeproductioninstancedomainop.py
clerk_dev/models/clerkerror.py
clerk_dev/models/clerkerrors.py
clerk_dev/models/client.py
clerk_dev/models/cnametarget.py
clerk_dev/models/createactortokenop.py
clerk_dev/models/createallowlistidentifierop.py
clerk_dev/models/createblocklistidentifierop.py
clerk_dev/models/createemailaddressop.py
clerk_dev/models/createinvitationop.py
clerk_dev/models/createjwttemplateop.py
clerk_dev/models/createoauthapplicationop.py
clerk_dev/models/createorganizationinvitationbulkop.py
clerk_dev/models/createorganizationinvitationop.py
clerk_dev/models/createorganizationmembershipop.py
clerk_dev/models/createorganizationop.py
clerk_dev/models/createphonenumberop.py
clerk_dev/models/createredirecturlop.py
clerk_dev/models/createsamlconnectionop.py
clerk_dev/models/createsessiontokenfromtemplateop.py
clerk_dev/models/createsignintokenop.py
clerk_dev/models/createuserop.py
clerk_dev/models/deleteallowlistidentifierop.py
clerk_dev/models/deleteblocklistidentifierop.py
clerk_dev/models/deletedobject.py
clerk_dev/models/deletedomainop.py
clerk_dev/models/deleteemailaddressop.py
clerk_dev/models/deletejwttemplateop.py
clerk_dev/models/deleteoauthapplicationop.py
clerk_dev-0.5.0a4.dist-info/METADATA
clerk_dev-0.5.0a4.dist-info/WHEEL
clerk_dev-0.5.0a4.dist-info/RECORD
